skclean/__init__.py
skclean/pipeline.py
skclean/simulate_noise.py
skclean/datasets/__init__.py
skclean/datasets/breast_cancer.csv
skclean/datasets/iris.csv
skclean/datasets/optdigits.csv
skclean/datasets/spambase.csv
skclean/datasets/vowel.csv
skclean/detectors/__init__.py
skclean/detectors/base.py
skclean/detectors/ensemble.py
skclean/detectors/neighbors.py
skclean/handlers/__init__.py
skclean/handlers/base.py
skclean/handlers/example_weighting.py
skclean/handlers/filters.py
skclean/models/__init__.py
skclean/models/ensemble.py
skclean/models/logistic_regression.py
skclean/models/svm.py
skclean/tests/__init__.py
skclean/tests/common_stuff.py
skclean/tests/test_all_estimators.py
skclean/tests/test_noise_simulation.py
skclean/tests/test_pipeline_skclean.py
skclean/tests/test_pipeline_sklearn.py
skclean/tests/test_readme.py
skclean/tests/test_utils.py
skclean/utils/__init__.py
skclean/utils/_utils.py
skclean/utils/noise_generation.py
skclean/utils/testing.py
scikit_clean-0.1.2.dist-info/LICENSE
scikit_clean-0.1.2.dist-info/METADATA
scikit_clean-0.1.2.dist-info/WHEEL
scikit_clean-0.1.2.dist-info/top_level.txt
scikit_clean-0.1.2.dist-info/RECORD
