Metadata-Version: 2.1
Name: scikit-clean
Version: 0.1.2
Summary: A collection of algorithms for detecting and handling label noise
Home-page: https://github.com/Shihab-Shahriar/scikit-clean
Maintainer: Shihab Shahriar Khan
Maintainer-email: redoykhan555@gmail.com
License: MIT
Download-URL: https://github.com/Shihab-Shahriar/scikit-clean
Platform: UNKNOWN
Classifier: Intended Audience :: Science/Research
Classifier: License :: OSI Approved
Classifier: Programming Language :: Python
Classifier: Topic :: Software Development
Classifier: Topic :: Scientific/Engineering
Classifier: Operating System :: Microsoft :: Windows
Classifier: Operating System :: POSIX
Classifier: Operating System :: Unix
Classifier: Operating System :: MacOS
Classifier: Programming Language :: Python :: 3.7
Classifier: Programming Language :: Python :: 3.8
Requires-Dist: scikit-learn (>=0.23)
Requires-Dist: pandas (>=1.0)
